font_obfuscator/__init__.py
font_obfuscator/default.ttf
font_obfuscator/obf.py
font_obfuscator-0.1.2.dist-info/LICENSE
font_obfuscator-0.1.2.dist-info/METADATA
font_obfuscator-0.1.2.dist-info/WHEEL
font_obfuscator-0.1.2.dist-info/RECORD
