Metadata-Version: 2.1
Name: font-obfuscator
Version: 0.1.2
Summary: 
Home-page: https://github.com/ma-pony/font-obfuscator
Author: Pony.Ma
Author-email: mtf201013@gmail.com
Requires-Python: >=3.10,<4.0
Classifier: Programming Language :: Python :: 3
Classifier: Programming Language :: Python :: 3.10
Classifier: Programming Language :: Python :: 3.11
Classifier: Programming Language :: Python :: 3.12
Requires-Dist: fonttools[lxml,ufo,unicode,woff] (>=4.53.1,<5.0.0)
Project-URL: Repository, https://github.com/ma-pony/font-obfuscator
